Workbook

Sheet Inputs_Target
A1: Company | B1: Ticker | C1: Revenue LTM | D1: EBITDA LTM | E1: Net Income LTM | F1: Net Debt | G1: Shares Outstanding | H1: Current Price
A2: PayPal Holdings | B2: PYPL | C2: 30000 | D2: 6000 | E2: 4200 | F2: -2000 | G2: 1150 | H2: 62
A3: Financials in USD millions except per-share data.

Sheet Comps
A1: Ticker | B1: Company | C1: Market Cap | D1: Net Debt | E1: Enterprise Value (EV) | F1: Revenue LTM | G1: EBITDA LTM | H1: Net Income LTM | I1: EV/Revenue | J1: EV/EBITDA | K1: P/E
A2: SQ | B2: Block | C2: 65000 | D2: -1500 | E2: =C2+D2 -> 63500 | F2: 32000 | G2: 7000 | H2: 800 | I2: =IFERROR(E2/F2,"") -> 1.984375 | J2: =IFERROR(E2/G2,"") -> 9.0714286 | K2: =IFERROR(C2/H2,"") -> 81.25
A3: AXP | B3: AmEx | C3: 40000 | D3: 17000 | E3: =C3+D3 -> 57000 | F3: 10000 | G3: 3800 | H3: 9000 | I3: =IFERROR(E3/F3,"") -> 5.7 | J3: =IFERROR(E3/G3,"") -> 15 | K3: =IFERROR(C3/H3,"") -> 4.4444444
A4: V | B4: Visa | C4: 52000 | D4: 14000 | E4: =C4+D4 -> 66000 | F4: 14000 | G4: 4600 | H4: 18000 | I4: =IFERROR(E4/F4,"") -> 4.7142857 | J4: =IFERROR(E4/G4,"") -> 14.347826 | K4: =IFERROR(C4/H4,"") -> 2.8888889
A5: MA | B5: Mastercard | C5: 70000 | D5: 18000 | E5: =C5+D5 -> 88000 | F5: 19000 | G5: 6500 | H5: 12000 | I5: =IFERROR(E5/F5,"") -> 4.6315789 | J5: =IFERROR(E5/G5,"") -> 13.538462 | K5: =IFERROR(C5/H5,"") -> 5.8333333
A6: GPN | B6: Global Payments | C6: 140000 | D6: 45000 | E6: =C6+D6 -> 185000 | F6: 65000 | G6: 23000 | H6: 1600 | I6: =IFERROR(E6/F6,"") -> 2.8461538 | J6: =IFERROR(E6/G6,"") -> 8.0434783 | K6: =IFERROR(C6/H6,"") -> 87.5
E7: =C7+D7 -> 0 | I7: =IFERROR(E7/F7,"") | J7: =IFERROR(C7/H7,"") | K7: =IFERROR(C7/H7,"")
E8: =C8+D8 -> 0 | I8: =IFERROR(E8/F8,"") | J8: =IFERROR(C8/H8,"") | K8: =IFERROR(C8/H8,"")
E9: =C9+D9 -> 0 | I9: =IFERROR(E9/F9,"") | J9: =IFERROR(C9/H9,"") | K9: =IFERROR(C9/H9,"")
E10: =C10+D10 -> 0 | I10: =IFERROR(E10/F10,"") | J10: =IFERROR(C10/H10,"") | K10: =IFERROR(C10/H10,"")
E11: =C11+D11 -> 0 | I11: =IFERROR(E11/F11,"") | J11: =IFERROR(C11/H11,"") | K11: =IFERROR(C11/H11,"")
E12: =C12+D12 -> 0 | I12: =IFERROR(E12/F12,"") | J12: =IFERROR(C12/H12,"") | K12: =IFERROR(C12/H12,"")
E13: =C13+D13 -> 0 | I13: =IFERROR(E13/F13,"") | J13: =IFERROR(C13/H13,"") | K13: =IFERROR(C13/H13,"")
H15: EV/Revenue
H16: 25th Percentile | I16: =_xlfn.QUARTILE.INC(I2:I13,1) -> 2.8461538
H17: Median | I17: =MEDIAN(I2:I13) -> 4.6315789
H18: 75th Percentile | I18: =_xlfn.QUARTILE.INC(I2:I13,3) -> 4.7142857
H20: EV / EBITDA
H21: 25th Percentile | J21: =_xlfn.QUARTILE.INC(J2:J13,1) -> 9.0714286
H22: Median | J22: {=MEDIAN(IF(G2:G13>0,J2:J13))} -> 13.538462
H23: 75th Percentile | J23: =_xlfn.QUARTILE.INC(J2:J13,3) -> 14.347826
H25: P / E
H26: 25th Percentile | K26: =_xlfn.QUARTILE.INC(K2:K13,1) -> 4.4444444
H27: Median | K27: =MEDIAN(K2:K13) -> 5.8333333
H28: 75th Percentile | K28: =_xlfn.QUARTILE.INC(K2:K13,3) -> 81.25

Sheet Precedents
A1: Announce Date | B1: Acquirer | C1: Target | D1: Industry | E1: Deal EV | F1: Revenue LTM | G1: EBITDA LTM | H1: EV/Revenue | I1: EV/EBITDA | J1: Deal type | K1: Source | L1: Adj EV/EBITDA
A2: 2021 | B2: FIS | C2: Worldpay | D2: Payments | E2: 43000 | F2: 12000 | G2: 4200 | H2: =IFERROR(E2/F2,"") -> 3.5833333 | I2: =IFERROR(E2/G2,"") -> 10.238095 | J2: LBO | K2: Press | L2: =IF(G2>0,I2,"") -> 10.238095
A3: 2020 | B3: FISV | C3: First Data | D3: Payments | E3: 39000 | F3: 9500 | G3: 3800 | H3: =IFERROR(E3/F3,"") -> 4.1052632 | I3: =IFERROR(E3/G3,"") -> 10.263158 | J3: Strategic | K3: Press | L3: =IF(G3>0,I3,"") -> 10.263158
A4: 2019 | B4: PayPal | C4: iZettle | D4: Payments | E4: 2200 | F4: 500 | G4: 120 | H4: =IFERROR(E4/F4,"") -> 4.4 | I4: =IFERROR(E4/G4,"") -> 18.333333 | J4: Strategic | K4: Press | L4: =IF(G4>0,I4,"") -> 18.333333
A5: 2022 | B5: Stripe | C5: Bouncer | D5: Payments | E5: 21000 | F5: 5000 | G5: 1800 | H5: =IFERROR(E5/F5,"") -> 4.2 | I5: =IFERROR(E5/G5,"") -> 11.666667 | J5: Strategic | K5: Press | L5: =IF(G5>0,I5,"") -> 11.666667
H6: =IFERROR(E6/F6,"") | I6: =IFERROR(E6/G6,"") | L6: =IF(G6>0,I6,"")
H7: =IFERROR(E7/F7,"") | I7: =IFERROR(E7/G7,"") | L7: =IF(G7>0,I7,"")
H8: =IFERROR(E8/F8,"") | I8: =IFERROR(E8/G8,"") | L8: =IF(G8>0,I8,"")
H9: =IFERROR(E9/F9,"") | I9: =IFERROR(E9/G9,"") | L9: =IF(G9>0,I9,"")
H10: =IFERROR(E10/F10,"") | I10: =IFERROR(E10/G10,"") | L10: =IF(G10>0,I10,"")
G12: EV / Revenue
G13: 25th Percentile | H13: =_xlfn.QUARTILE.INC(H2:H10,1) -> 3.9747807
G14: Median | H14: =MEDIAN(H2:H10) -> 4.1526316
G15: 75th Percentile | H15: =_xlfn.QUARTILE.INC(H2:H10,3) -> 4.25
G17: EV / EBITDA
G18: 25th Percentile | I18: =_xlfn.QUARTILE.INC($L$2:$L$10,1) -> 10.256892
G19: Median | I19: =MEDIAN($L$2:$L$10) -> 10.964912
G20: 75th Percentile | I20: =_xlfn.QUARTILE.INC($L$2:$L$10,3) -> 13.333333

Sheet Valuation_Output
B1: P25 Multiple | C1: Median Multiple | D1: P75 Multiple | E1: Target Metric | F1: Implied EV (Low) | G1: Implied EV (Mid) | H1: Implied EV (High) | I1: Net Debt | J1: Equity Value (Low) | K1: Equity Value (Mid) | L1: Equity Value (High) | M1: Shares Outstanding | N1: Price / Share (Low) | O1: Price / Share (Mid) | P1: Price / Share (High) | R1: Method | S1: Low | T1: Mid | U1: High | V1: Range
A2: Comps EV/Revenue | B2: =Comps!I16 -> 2.8461538 | C2: =Comps!I17 -> 4.6315789 | D2: =Comps!I18 -> 4.7142857 | E2: =Inputs_Target!C2 -> 30000 | F2: =B2 * E2 -> 85384.615 | G2: =C2 * E2 -> 138947.37 | H2: =D2 * E2 -> 141428.57 | I2: =Inputs_Target!F2 -> -2000 | J2: =F2 - I2 -> 87384.615 | K2: =G2 - I2 -> 140947.37 | L2: =H2 - I2 -> 143428.57 | M2: =Inputs_Target!$G$2 -> 1150 | N2: =J2 / M2 -> 75.986622 | O2: =K2 / M2 -> 122.56293 | P2: =L2 / M2 -> 124.7205 | R2: Comps EV/Revenue | S2: =IFERROR(Valuation_Output!N2,"") -> 75.986622 | T2: =IFERROR(Valuation_Output!O2,"") -> 122.56293 | U2: =IFERROR(Valuation_Output!P2,"") -> 124.7205 | V2: =IFERROR(U2-S2,"") -> 48.733875 | X2: =Inputs_Target!H2 -> 62 | Y2: 0.5
A3: Comps EV/EBITDA | B3: =Comps!J21 -> 9.0714286 | C3: =Comps!J22 -> 13.538462 | D3: =Comps!J23 -> 14.347826 | E3: =Inputs_Target!C2 -> 30000 | F3: =B3 * E3 -> 272142.86 | G3: =C3 * E3 -> 406153.85 | H3: =D3 * E3 -> 430434.78 | I3: =Inputs_Target!F2 -> -2000 | J3: =F3 - I3 -> 274142.86 | K3: =G3 - I3 -> 408153.85 | L3: =H3 - I3 -> 432434.78 | M3: =Inputs_Target!$G$2 -> 1150 | N3: =J3 / M3 -> 238.38509 | O3: =K3 / M3 -> 354.91639 | P3: =L3 / M3 -> 376.03025 | R3: Comps EV/EBITDA | S3: =NA() -> #N/A | T3: =NA() -> #N/A | U3: =NA() -> #N/A | V3: =NA() -> #N/A | X3: =Inputs_Target!H2 -> 62 | Y3: 4.5
A4: Precedents EV/Revenue | B4: =Precedents!H13 -> 3.9747807 | C4: =Precedents!H14 -> 4.1526316 | D4: =Precedents!H15 -> 4.25 | E4: =Inputs_Target!D2 -> 6000 | F4: =B4 * E4 -> 23848.684 | G4: =C4 * E4 -> 24915.789 | H4: =D4 * E4 -> 25500 | I4: =Inputs_Target!F2 -> -2000 | J4: =F4 - I4 -> 25848.684 | K4: =G4 - I4 -> 26915.789 | L4: =H4 - I4 -> 27500 | M4: =Inputs_Target!$G$2 -> 1150 | N4: =J4 / M4 -> 22.477117 | O4: =K4 / M4 -> 23.405034 | P4: =L4 / M4 -> 23.913043 | R4: Precedents EV/Revenue | S4: =IFERROR(Valuation_Output!N4,"") -> 22.477117 | T4: =IFERROR(Valuation_Output!O4,"") -> 23.405034 | U4: =IFERROR(Valuation_Output!P4,"") -> 23.913043 | V4: =IFERROR(U4-S4,"") -> 1.4359268
A5: Precedents EV/EBITDA | B5: =Precedents!I18 -> 10.256892 | C5: =Precedents!I19 -> 10.964912 | D5: =Precedents!I20 -> 13.333333 | E5: =Inputs_Target!D2 -> 6000 | F5: =B5 * E5 -> 61541.353 | G5: =C5 * E5 -> 65789.474 | H5: =D5 * E5 -> 80000 | I5: =Inputs_Target!F2 -> -2000 | J5: =F5 - I5 -> 63541.353 | K5: =G5 - I5 -> 67789.474 | L5: =H5 - I5 -> 82000 | M5: =Inputs_Target!$G$2 -> 1150 | N5: =J5 / M5 -> 55.253351 | O5: =K5 / M5 -> 58.947368 | P5: =L5 / M5 -> 71.304348 | R5: Precedents EV/EBITDA | S5: =IFERROR(Valuation_Output!N5,"") -> 55.253351 | T5: =IFERROR(Valuation_Output!O5,"") -> 58.947368 | U5: =IFERROR(Valuation_Output!P5,"") -> 71.304348 | V5: =IFERROR(U5-S5,"") -> 16.050997
X9: Valuation ranges reflect P25–P75 multiples. EV/EBITDA is treated as the primary valuation method, with EV/Revenue used as a secondary cross-check. The vertical line denotes the current share price. Certain EV/EBITDA-based trading multiples were excluded where margin differences among peers produced disproportionately high implied values.

Sheet Assumptions_NotesNotes
A1: Revenue, EBITDA, and net income are in USD millions. Net debt is negative as the company holds net cash. Shares outstanding are in millions.
